{"card_name": "Streetsmart Gambler", "color": "UR", "rarity": "uncommon", "type": "Creature \u2013 Human Wizard", "number": 238, "color_identity": "UR", "cost": "{U}{R}", "rules_text": "Whenever you roll one or more dice, target creature you control gains +1/+1 until end of turn.\n{1}{U}{R}: Roll a d6. Exile the top X cards of your library, where X is half of the result rounded up. You may play those cards until the end of your next turn.", "flavor_text": "[i][/i]", "pt": "2/2", "special_text": "", "shape": "normal", "set": "HEX", "loyalty": "", "artist": "Altered TCG", "notes": "", "image_type": "png"}